<?xml version="1.0" encoding="UTF-8" standalone="yes"?>
<Path>
    <Pose>
        <x>0.0</x>
        <y>0.0</y>
        <heading>0.0</heading>
        <isVertex>true</isVertex>
    </Pose>
    <Pose>
        <x>0.0</x>
        <y>0.4</y>
        <heading>0.0</heading>
        <isVertex>false</isVertex>
    </Pose>
    <Pose>
        <x>0.0</x>
        <y>0.8</y>
        <heading>0.0</heading>
        <isVertex>false</isVertex>
    </Pose>
    <Pose>
        <x>0.0</x>
        <y>1.2</y>
        <heading>0.0</heading>
        <isVertex>false</isVertex>
    </Pose>
    <Pose>
        <x>0.0</x>
        <y>1.6</y>
        <heading>0.0</heading>
        <isVertex>false</isVertex>
    </Pose>
    <Pose>
        <x>0.0</x>
        <y>2.0</y>
        <heading>0.0</heading>
        <isVertex>false</isVertex>
    </Pose>
    <Pose>
        <x>0.0</x>
        <y>2.4</y>
        <heading>0.0</heading>
        <isVertex>false</isVertex>
    </Pose>
    <Pose>
        <x>0.0</x>
        <y>2.8</y>
        <heading>0.0</heading>
        <isVertex>false</isVertex>
    </Pose>
    <Pose>
        <x>0.0</x>
        <y>3.2</y>
        <heading>0.0</heading>
        <isVertex>false</isVertex>
    </Pose>
    <Pose>
        <x>0.0</x>
        <y>3.6</y>
        <heading>0.0</heading>
        <isVertex>false</isVertex>
    </Pose>
    <Pose>
        <x>0.0</x>
        <y>4.0</y>
        <heading>0.0</heading>
        <isVertex>false</isVertex>
    </Pose>
    <Pose>
        <x>0.0</x>
        <y>4.4</y>
        <heading>0.0</heading>
        <isVertex>false</isVertex>
    </Pose>
    <Pose>
        <x>0.0</x>
        <y>4.8</y>
        <heading>0.0</heading>
        <isVertex>false</isVertex>
    </Pose>
    <Pose>
        <x>0.0</x>
        <y>5.2</y>
        <heading>0.0</heading>
        <isVertex>false</isVertex>
    </Pose>
    <Pose>
        <x>0.0</x>
        <y>5.6</y>
        <heading>0.0</heading>
        <isVertex>false</isVertex>
    </Pose>
    <Pose>
        <x>0.0</x>
        <y>6.0</y>
        <heading>0.0</heading>
        <isVertex>false</isVertex>
    </Pose>
    <Pose>
        <x>0.0</x>
        <y>6.4</y>
        <heading>0.0</heading>
        <isVertex>false</isVertex>
    </Pose>
    <Pose>
        <x>0.0</x>
        <y>6.8</y>
        <heading>0.0</heading>
        <isVertex>false</isVertex>
    </Pose>
    <Pose>
        <x>0.0</x>
        <y>7.2</y>
        <heading>0.0</heading>
        <isVertex>false</isVertex>
    </Pose>
    <Pose>
        <x>0.0</x>
        <y>7.6</y>
        <heading>0.0</heading>
        <isVertex>false</isVertex>
    </Pose>
    <Pose>
        <x>0.0</x>
        <y>8.0</y>
        <heading>0.0</heading>
        <isVertex>false</isVertex>
    </Pose>
    <Pose>
        <x>0.0</x>
        <y>8.4</y>
        <heading>0.0</heading>
        <isVertex>false</isVertex>
    </Pose>
    <Pose>
        <x>0.0</x>
        <y>8.8</y>
        <heading>0.0</heading>
        <isVertex>false</isVertex>
    </Pose>
    <Pose>
        <x>0.0</x>
        <y>9.2</y>
        <heading>0.0</heading>
        <isVertex>false</isVertex>
    </Pose>
    <Pose>
        <x>0.0</x>
        <y>9.6</y>
        <heading>0.0</heading>
        <isVertex>false</isVertex>
    </Pose>
    <Pose>
        <x>0.0</x>
        <y>10.0</y>
        <heading>0.0</heading>
        <isVertex>false</isVertex>
    </Pose>
    <Pose>
        <x>0.0</x>
        <y>10.4</y>
        <heading>0.0</heading>
        <isVertex>false</isVertex>
    </Pose>
    <Pose>
        <x>0.0</x>
        <y>10.8</y>
        <heading>0.0</heading>
        <isVertex>false</isVertex>
    </Pose>
    <Pose>
        <x>0.0</x>
        <y>11.2</y>
        <heading>0.0</heading>
        <isVertex>false</isVertex>
    </Pose>
    <Pose>
        <x>0.0</x>
        <y>11.6</y>
        <heading>0.0</heading>
        <isVertex>false</isVertex>
    </Pose>
    <Pose>
        <x>0.0</x>
        <y>12.0</y>
        <heading>0.0</heading>
        <isVertex>false</isVertex>
    </Pose>
    <Pose>
        <x>0.0</x>
        <y>12.4</y>
        <heading>0.0</heading>
        <isVertex>false</isVertex>
    </Pose>
    <Pose>
        <x>0.0</x>
        <y>12.8</y>
        <heading>0.0</heading>
        <isVertex>false</isVertex>
    </Pose>
    <Pose>
        <x>0.0</x>
        <y>13.2</y>
        <heading>0.0</heading>
        <isVertex>false</isVertex>
    </Pose>
    <Pose>
        <x>0.0</x>
        <y>13.6</y>
        <heading>0.0</heading>
        <isVertex>false</isVertex>
    </Pose>
    <Pose>
        <x>0.0</x>
        <y>14.0</y>
        <heading>0.0</heading>
        <isVertex>false</isVertex>
    </Pose>
    <Pose>
        <x>0.0</x>
        <y>14.4</y>
        <heading>0.0</heading>
        <isVertex>false</isVertex>
    </Pose>
    <Pose>
        <x>0.0</x>
        <y>14.8</y>
        <heading>0.0</heading>
        <isVertex>false</isVertex>
    </Pose>
    <Pose>
        <x>0.0</x>
        <y>15.2</y>
        <heading>0.0</heading>
        <isVertex>false</isVertex>
    </Pose>
    <Pose>
        <x>0.0</x>
        <y>15.6</y>
        <heading>0.0</heading>
        <isVertex>false</isVertex>
    </Pose>
    <Pose>
        <x>0.0</x>
        <y>16.0</y>
        <heading>0.0</heading>
        <isVertex>false</isVertex>
    </Pose>
    <Pose>
        <x>0.0</x>
        <y>16.4</y>
        <heading>0.0</heading>
        <isVertex>false</isVertex>
    </Pose>
    <Pose>
        <x>0.0</x>
        <y>16.8</y>
        <heading>0.0</heading>
        <isVertex>false</isVertex>
    </Pose>
    <Pose>
        <x>0.0</x>
        <y>17.2</y>
        <heading>0.0</heading>
        <isVertex>false</isVertex>
    </Pose>
    <Pose>
        <x>0.0</x>
        <y>17.6</y>
        <heading>0.0</heading>
        <isVertex>false</isVertex>
    </Pose>
    <Pose>
        <x>0.0</x>
        <y>18.0</y>
        <heading>0.0</heading>
        <isVertex>false</isVertex>
    </Pose>
    <Pose>
        <x>0.0</x>
        <y>18.4</y>
        <heading>0.0</heading>
        <isVertex>false</isVertex>
    </Pose>
    <Pose>
        <x>0.0</x>
        <y>18.8</y>
        <heading>0.0</heading>
        <isVertex>false</isVertex>
    </Pose>
    <Pose>
        <x>0.0</x>
        <y>19.2</y>
        <heading>0.0</heading>
        <isVertex>false</isVertex>
    </Pose>
    <Pose>
        <x>0.0</x>
        <y>19.6</y>
        <heading>0.0</heading>
        <isVertex>false</isVertex>
    </Pose>
    <Pose>
        <x>0.0</x>
        <y>20.0</y>
        <heading>0.0</heading>
        <isVertex>false</isVertex>
    </Pose>
    <Pose>
        <x>0.0</x>
        <y>20.4</y>
        <heading>0.0</heading>
        <isVertex>false</isVertex>
    </Pose>
    <Pose>
        <x>0.0</x>
        <y>20.8</y>
        <heading>0.0</heading>
        <isVertex>false</isVertex>
    </Pose>
    <Pose>
        <x>0.0</x>
        <y>21.2</y>
        <heading>0.0</heading>
        <isVertex>false</isVertex>
    </Pose>
    <Pose>
        <x>0.0</x>
        <y>21.6</y>
        <heading>0.0</heading>
        <isVertex>false</isVertex>
    </Pose>
    <Pose>
        <x>0.0</x>
        <y>22.0</y>
        <heading>0.0</heading>
        <isVertex>false</isVertex>
    </Pose>
    <Pose>
        <x>0.0</x>
        <y>22.4</y>
        <heading>0.0</heading>
        <isVertex>false</isVertex>
    </Pose>
    <Pose>
        <x>0.0</x>
        <y>22.8</y>
        <heading>0.0</heading>
        <isVertex>false</isVertex>
    </Pose>
    <Pose>
        <x>0.0</x>
        <y>23.2</y>
        <heading>0.0</heading>
        <isVertex>false</isVertex>
    </Pose>
    <Pose>
        <x>0.0</x>
        <y>23.6</y>
        <heading>0.0</heading>
        <isVertex>false</isVertex>
    </Pose>
    <Pose>
        <x>0.0</x>
        <y>24.0</y>
        <heading>0.0</heading>
        <isVertex>false</isVertex>
    </Pose>
    <Pose>
        <x>0.0</x>
        <y>24.4</y>
        <heading>0.0</heading>
        <isVertex>false</isVertex>
    </Pose>
    <Pose>
        <x>0.0</x>
        <y>24.8</y>
        <heading>0.0</heading>
        <isVertex>false</isVertex>
    </Pose>
    <Pose>
        <x>0.0</x>
        <y>25.2</y>
        <heading>0.0</heading>
        <isVertex>false</isVertex>
    </Pose>
    <Pose>
        <x>0.0</x>
        <y>25.6</y>
        <heading>0.0</heading>
        <isVertex>false</isVertex>
    </Pose>
    <Pose>
        <x>0.0</x>
        <y>26.0</y>
        <heading>0.0</heading>
        <isVertex>false</isVertex>
    </Pose>
    <Pose>
        <x>0.0</x>
        <y>26.4</y>
        <heading>0.0</heading>
        <isVertex>false</isVertex>
    </Pose>
    <Pose>
        <x>0.0</x>
        <y>26.8</y>
        <heading>0.0</heading>
        <isVertex>false</isVertex>
    </Pose>
    <Pose>
        <x>0.0</x>
        <y>27.2</y>
        <heading>0.0</heading>
        <isVertex>false</isVertex>
    </Pose>
    <Pose>
        <x>0.0</x>
        <y>27.6</y>
        <heading>0.0</heading>
        <isVertex>false</isVertex>
    </Pose>
    <Pose>
        <x>0.0</x>
        <y>28.0</y>
        <heading>0.0</heading>
        <isVertex>false</isVertex>
    </Pose>
    <Pose>
        <x>0.0</x>
        <y>28.4</y>
        <heading>0.0</heading>
        <isVertex>false</isVertex>
    </Pose>
    <Pose>
        <x>0.0</x>
        <y>28.8</y>
        <heading>0.0</heading>
        <isVertex>false</isVertex>
    </Pose>
    <Pose>
        <x>0.0</x>
        <y>29.2</y>
        <heading>0.0</heading>
        <isVertex>false</isVertex>
    </Pose>
    <Pose>
        <x>0.0</x>
        <y>29.6</y>
        <heading>0.0</heading>
        <isVertex>false</isVertex>
    </Pose>
    <Pose>
        <x>0.0</x>
        <y>30.0</y>
        <heading>0.0</heading>
        <isVertex>false</isVertex>
    </Pose>
    <Pose>
        <x>0.0</x>
        <y>30.4</y>
        <heading>0.0</heading>
        <isVertex>false</isVertex>
    </Pose>
    <Pose>
        <x>0.0</x>
        <y>30.8</y>
        <heading>0.0</heading>
        <isVertex>false</isVertex>
    </Pose>
    <Pose>
        <x>0.0</x>
        <y>31.2</y>
        <heading>0.0</heading>
        <isVertex>false</isVertex>
    </Pose>
    <Pose>
        <x>0.0</x>
        <y>31.6</y>
        <heading>0.0</heading>
        <isVertex>false</isVertex>
    </Pose>
    <Pose>
        <x>0.0</x>
        <y>32.0</y>
        <heading>0.0</heading>
        <isVertex>false</isVertex>
    </Pose>
    <Pose>
        <x>0.0</x>
        <y>32.4</y>
        <heading>0.0</heading>
        <isVertex>false</isVertex>
    </Pose>
    <Pose>
        <x>0.0</x>
        <y>32.8</y>
        <heading>0.0</heading>
        <isVertex>false</isVertex>
    </Pose>
    <Pose>
        <x>0.0</x>
        <y>33.2</y>
        <heading>0.0</heading>
        <isVertex>false</isVertex>
    </Pose>
    <Pose>
        <x>0.0</x>
        <y>33.6</y>
        <heading>0.0</heading>
        <isVertex>false</isVertex>
    </Pose>
    <Pose>
        <x>0.0</x>
        <y>34.0</y>
        <heading>0.0</heading>
        <isVertex>false</isVertex>
    </Pose>
    <Pose>
        <x>0.0</x>
        <y>34.4</y>
        <heading>0.0</heading>
        <isVertex>false</isVertex>
    </Pose>
    <Pose>
        <x>0.0</x>
        <y>34.8</y>
        <heading>0.0</heading>
        <isVertex>false</isVertex>
    </Pose>
    <Pose>
        <x>0.0</x>
        <y>35.2</y>
        <heading>0.0</heading>
        <isVertex>false</isVertex>
    </Pose>
    <Pose>
        <x>0.0</x>
        <y>35.6</y>
        <heading>0.0</heading>
        <isVertex>false</isVertex>
    </Pose>
    <Pose>
        <x>0.0</x>
        <y>36.0</y>
        <heading>0.0</heading>
        <isVertex>false</isVertex>
    </Pose>
    <Pose>
        <x>0.0</x>
        <y>36.4</y>
        <heading>0.0</heading>
        <isVertex>false</isVertex>
    </Pose>
    <Pose>
        <x>0.0</x>
        <y>36.8</y>
        <heading>0.0</heading>
        <isVertex>false</isVertex>
    </Pose>
    <Pose>
        <x>0.0</x>
        <y>37.2</y>
        <heading>0.0</heading>
        <isVertex>false</isVertex>
    </Pose>
    <Pose>
        <x>0.0</x>
        <y>37.6</y>
        <heading>0.0</heading>
        <isVertex>false</isVertex>
    </Pose>
    <Pose>
        <x>0.0</x>
        <y>38.0</y>
        <heading>0.0</heading>
        <isVertex>false</isVertex>
    </Pose>
    <Pose>
        <x>0.0</x>
        <y>38.4</y>
        <heading>0.0</heading>
        <isVertex>false</isVertex>
    </Pose>
    <Pose>
        <x>0.0</x>
        <y>38.8</y>
        <heading>0.0</heading>
        <isVertex>false</isVertex>
    </Pose>
    <Pose>
        <x>0.0</x>
        <y>39.2</y>
        <heading>0.0</heading>
        <isVertex>false</isVertex>
    </Pose>
    <Pose>
        <x>0.0</x>
        <y>39.6</y>
        <heading>0.0</heading>
        <isVertex>false</isVertex>
    </Pose>
    <Pose>
        <x>0.0</x>
        <y>40.0</y>
        <heading>0.0</heading>
        <isVertex>false</isVertex>
    </Pose>
    <Pose>
        <x>0.0</x>
        <y>40.4</y>
        <heading>0.0</heading>
        <isVertex>false</isVertex>
    </Pose>
    <Pose>
        <x>0.0</x>
        <y>40.8</y>
        <heading>0.0</heading>
        <isVertex>false</isVertex>
    </Pose>
    <Pose>
        <x>0.0</x>
        <y>41.2</y>
        <heading>0.0</heading>
        <isVertex>false</isVertex>
    </Pose>
    <Pose>
        <x>0.0</x>
        <y>41.6</y>
        <heading>0.0</heading>
        <isVertex>false</isVertex>
    </Pose>
    <Pose>
        <x>0.0</x>
        <y>42.0</y>
        <heading>0.0</heading>
        <isVertex>false</isVertex>
    </Pose>
    <Pose>
        <x>0.0</x>
        <y>42.4</y>
        <heading>0.0</heading>
        <isVertex>false</isVertex>
    </Pose>
    <Pose>
        <x>0.0</x>
        <y>42.8</y>
        <heading>0.0</heading>
        <isVertex>false</isVertex>
    </Pose>
    <Pose>
        <x>0.0</x>
        <y>43.2</y>
        <heading>0.0</heading>
        <isVertex>false</isVertex>
    </Pose>
    <Pose>
        <x>0.0</x>
        <y>43.6</y>
        <heading>0.0</heading>
        <isVertex>false</isVertex>
    </Pose>
    <Pose>
        <x>0.0</x>
        <y>44.0</y>
        <heading>0.0</heading>
        <isVertex>false</isVertex>
    </Pose>
    <Pose>
        <x>0.0</x>
        <y>44.4</y>
        <heading>0.0</heading>
        <isVertex>false</isVertex>
    </Pose>
    <Pose>
        <x>0.0</x>
        <y>44.8</y>
        <heading>0.0</heading>
        <isVertex>false</isVertex>
    </Pose>
    <Pose>
        <x>0.0</x>
        <y>45.2</y>
        <heading>0.0</heading>
        <isVertex>false</isVertex>
    </Pose>
    <Pose>
        <x>0.0</x>
        <y>45.6</y>
        <heading>0.0</heading>
        <isVertex>false</isVertex>
    </Pose>
    <Pose>
        <x>0.0</x>
        <y>46.0</y>
        <heading>0.0</heading>
        <isVertex>false</isVertex>
    </Pose>
    <Pose>
        <x>0.0</x>
        <y>46.4</y>
        <heading>0.0</heading>
        <isVertex>false</isVertex>
    </Pose>
    <Pose>
        <x>0.0</x>
        <y>46.8</y>
        <heading>0.0</heading>
        <isVertex>false</isVertex>
    </Pose>
    <Pose>
        <x>0.0</x>
        <y>47.2</y>
        <heading>0.0</heading>
        <isVertex>false</isVertex>
    </Pose>
    <Pose>
        <x>0.0</x>
        <y>47.6</y>
        <heading>0.0</heading>
        <isVertex>false</isVertex>
    </Pose>
    <Pose>
        <x>0.0</x>
        <y>48.0</y>
        <heading>0.0</heading>
        <isVertex>false</isVertex>
    </Pose>
    <Pose>
        <x>0.0</x>
        <y>48.4</y>
        <heading>0.0</heading>
        <isVertex>false</isVertex>
    </Pose>
    <Pose>
        <x>0.0</x>
        <y>48.8</y>
        <heading>0.0</heading>
        <isVertex>false</isVertex>
    </Pose>
    <Pose>
        <x>0.0</x>
        <y>49.2</y>
        <heading>0.0</heading>
        <isVertex>false</isVertex>
    </Pose>
    <Pose>
        <x>0.0</x>
        <y>49.6</y>
        <heading>0.0</heading>
        <isVertex>false</isVertex>
    </Pose>
    <Pose>
        <x>0.0</x>
        <y>50.0</y>
        <heading>0.0</heading>
        <isVertex>false</isVertex>
    </Pose>
    <Pose>
        <x>0.0</x>
        <y>50.4</y>
        <heading>0.0</heading>
        <isVertex>false</isVertex>
    </Pose>
    <Pose>
        <x>0.0</x>
        <y>50.8</y>
        <heading>0.0</heading>
        <isVertex>false</isVertex>
    </Pose>
    <Pose>
        <x>0.0</x>
        <y>51.2</y>
        <heading>0.0</heading>
        <isVertex>false</isVertex>
    </Pose>
    <Pose>
        <x>0.0</x>
        <y>51.6</y>
        <heading>0.0</heading>
        <isVertex>false</isVertex>
    </Pose>
    <Pose>
        <x>0.0</x>
        <y>52.0</y>
        <heading>0.0</heading>
        <isVertex>false</isVertex>
    </Pose>
    <Pose>
        <x>0.0</x>
        <y>52.4</y>
        <heading>0.0</heading>
        <isVertex>false</isVertex>
    </Pose>
    <Pose>
        <x>0.003999866668443985</x>
        <y>52.39997333386666</y>
        <heading>0.0</heading>
        <isVertex>false</isVertex>
    </Pose>
    <Pose>
        <x>0.015997866780441683</x>
        <y>52.799786683732684</y>
        <heading>0.0</heading>
        <isVertex>false</isVertex>
    </Pose>
    <Pose>
        <x>0.03598920129591576</x>
        <y>53.19928012958889</y>
        <heading>0.0</heading>
        <isVertex>false</isVertex>
    </Pose>
    <Pose>
        <x>0.06396587394761255</x>
        <y>53.598293879383455</y>
        <heading>0.0</heading>
        <isVertex>false</isVertex>
    </Pose>
    <Pose>
        <x>0.09991669443948581</x>
        <y>53.996668332936565</y>
        <heading>0.0</heading>
        <isVertex>false</isVertex>
    </Pose>
    <Pose>
        <x>0.14382728292267544</x>
        <y>54.39424414577839</y>
        <heading>0.0</heading>
        <isVertex>false</isVertex>
    </Pose>
    <Pose>
        <x>0.19568007574725854</x>
        <y>54.79086229288473</y>
        <heading>0.0</heading>
        <isVertex>false</isVertex>
    </Pose>
    <Pose>
        <x>0.2554543324874601</x>
        <y>55.18636413228492</y>
        <heading>0.0</heading>
        <isVertex>false</isVertex>
    </Pose>
    <Pose>
        <x>0.3231261442375697</x>
        <y>55.58059146851649</y>
        <heading>0.0</heading>
        <isVertex>false</isVertex>
    </Pose>
    <Pose>
        <x>0.39866844317516836</x>
        <y>55.97338661590123</y>
        <heading>0.0</heading>
        <isVertex>false</isVertex>
    </Pose>
    <Pose>
        <x>0.48205101338788836</x>
        <y>56.364592461617384</y>
        <heading>0.0</heading>
        <isVertex>false</isVertex>
    </Pose>
    <Pose>
        <x>0.5732405029594076</x>
        <y>56.754052528542694</y>
        <heading>0.0</heading>
        <isVertex>false</isVertex>
    </Pose>
    <Pose>
        <x>0.672200437309737</x>
        <y>57.141611037843106</y>
        <heading>0.0</heading>
        <isVertex>false</isVertex>
    </Pose>
    <Pose>
        <x>0.7788912337845808</x>
        <y>57.52711297128228</y>
        <heading>0.0</heading>
        <isVertex>false</isVertex>
    </Pose>
    <Pose>
        <x>0.8932702174878813</x>
        <y>57.91040413322679</y>
        <heading>0.0</heading>
        <isVertex>false</isVertex>
    </Pose>
    <Pose>
        <x>1.015291638351183</x>
        <y>58.291331212322355</y>
        <heading>0.0</heading>
        <isVertex>false</isVertex>
    </Pose>
    <Pose>
        <x>1.1449066894330748</x>
        <y>58.669741842816286</y>
        <heading>0.0</heading>
        <isVertex>false</isVertex>
    </Pose>
    <Pose>
        <x>1.2820635264413056</x>
        <y>59.0454846655018</y>
        <heading>0.0</heading>
        <isVertex>false</isVertex>
    </Pose>
    <Pose>
        <x>1.426707288469796</x>
        <y>59.418409388259654</y>
        <heading>0.0</heading>
        <isVertex>false</isVertex>
    </Pose>
    <Pose>
        <x>1.578780119942298</x>
        <y>59.78836684617301</y>
        <heading>0.0</heading>
        <isVertex>false</isVertex>
    </Pose>
    <Pose>
        <x>1.7382211937538337</x>
        <y>60.15520906119141</y>
        <heading>0.0</heading>
        <isVertex>false</isVertex>
    </Pose>
    <Pose>
        <x>1.904966735600734</x>
        <y>60.51878930131999</y>
        <heading>0.0</heading>
        <isVertex>false</isVertex>
    </Pose>
    <Pose>
        <x>2.078950049489496</x>
        <y>60.878962139310396</y>
        <heading>0.0</heading>
        <isVertex>false</isVertex>
    </Pose>
    <Pose>
        <x>2.2601015444143187</x>
        <y>61.235583510829656</y>
        <heading>0.0</heading>
        <isVertex>false</isVertex>
    </Pose>
    <Pose>
        <x>2.4483487621925484</x>
        <y>61.588510772084064</y>
        <heading>0.0</heading>
        <isVertex>false</isVertex>
    </Pose>
    <Pose>
        <x>2.643616406447002</x>
        <y>61.93760275687474</y>
        <heading>0.0</heading>
        <isVertex>false</isVertex>
    </Pose>
    <Pose>
        <x>2.8458263727235185</x>
        <y>62.28271983306226</y>
        <heading>0.0</heading>
        <isVertex>false</isVertex>
    </Pose>
    <Pose>
        <x>3.0548977797316788</x>
        <y>62.62372395841767</y>
        <heading>0.0</heading>
        <isVertex>false</isVertex>
    </Pose>
    <Pose>
        <x>3.270747001696261</x>
        <y>62.96047873583747</y>
        <heading>0.0</heading>
        <isVertex>false</isVertex>
    </Pose>
    <Pose>
        <x>3.4932877018064374</x>
        <y>63.29284946790071</y>
        <heading>0.0</heading>
        <isVertex>false</isVertex>
    </Pose>
    <Pose>
        <x>3.7224308667493204</x>
        <y>63.6207032107461</y>
        <heading>0.0</heading>
        <isVertex>false</isVertex>
    </Pose>
    <Pose>
        <x>3.9580848423141504</x>
        <y>63.94390882724784</y>
        <heading>0.0</heading>
        <isVertex>false</isVertex>
    </Pose>
    <Pose>
        <x>4.2001553700527</x>
        <y>64.26233703946868</y>
        <heading>0.0</heading>
        <isVertex>false</isVertex>
    </Pose>
    <Pose>
        <x>4.448545624981444</x>
        <y>64.57586048036937</y>
        <heading>0.0</heading>
        <isVertex>false</isVertex>
    </Pose>
    <Pose>
        <x>4.703156254310235</x>
        <y>64.88435374475382</y>
        <heading>0.0</heading>
        <isVertex>false</isVertex>
    </Pose>
    <Pose>
        <x>4.963885417182103</x>
        <y>65.18769343942947</y>
        <heading>0.0</heading>
        <isVertex>false</isVertex>
    </Pose>
    <Pose>
        <x>5.2306288254082425</x>
        <y>65.4857582325629</y>
        <heading>0.0</heading>
        <isVertex>false</isVertex>
    </Pose>
    <Pose>
        <x>5.503279785181899</x>
        <y>65.77842890221103</y>
        <heading>0.0</heading>
        <isVertex>false</isVertex>
    </Pose>
    <Pose>
        <x>5.781729239754455</x>
        <y>66.06558838400821</y>
        <heading>0.0</heading>
        <isVertex>false</isVertex>
    </Pose>
    <Pose>
        <x>6.0658658130566945</x>
        <y>66.34712181799046</y>
        <heading>0.0</heading>
        <isVertex>false</isVertex>
    </Pose>
    <Pose>
        <x>6.355575854247732</x>
        <y>66.62291659453791</y>
        <heading>0.0</heading>
        <isVertex>false</isVertex>
    </Pose>
    <Pose>
        <x>6.650743483173841</x>
        <y>66.89286239941718</y>
        <heading>0.0</heading>
        <isVertex>false</isVertex>
    </Pose>
    <Pose>
        <x>6.951250636718967</x>
        <y>67.15685125790554</y>
        <heading>0.0</heading>
        <isVertex>false</isVertex>
    </Pose>
    <Pose>
        <x>7.2569771160283985</x>
        <y>67.4147775779794</y>
        <heading>0.0</heading>
        <isVertex>false</isVertex>
    </Pose>
    <Pose>
        <x>7.567800634586712</x>
        <y>67.66653819254967</y>
        <heading>0.0</heading>
        <isVertex>false</isVertex>
    </Pose>
    <Pose>
        <x>7.883596867130747</x>
        <y>67.91203240072733</y>
        <heading>0.0</heading>
        <isVertex>false</isVertex>
    </Pose>
    <Pose>
        <x>8.204239499378039</x>
        <y>68.15116200810229</y>
        <heading>0.0</heading>
        <isVertex>false</isVertex>
    </Pose>
    <Pose>
        <x>8.52960027855087</x>
        <y>68.38383136601996</y>
        <heading>0.0</heading>
        <isVertex>false</isVertex>
    </Pose>
    <Pose>
        <x>8.859549064675658</x>
        <y>68.6099474098394</y>
        <heading>0.0</heading>
        <isVertex>false</isVertex>
    </Pose>
    <Pose>
        <x>9.19395388263721</x>
        <y>68.82941969615793</y>
        <heading>0.0</heading>
        <isVertex>false</isVertex>
    </Pose>
    <Pose>
        <x>9.532680974967015</x>
        <y>69.04216043898725</y>
        <heading>0.0</heading>
        <isVertex>false</isVertex>
    </Pose>
    <Pose>
        <x>9.875594855344437</x>
        <y>69.24808454486677</y>
        <heading>0.0</heading>
        <isVertex>false</isVertex>
    </Pose>
    <Pose>
        <x>10.222558362789453</x>
        <y>69.44710964689972</y>
        <heading>0.0</heading>
        <isVertex>false</isVertex>
    </Pose>
    <Pose>
        <x>10.573432716525206</x>
        <y>69.63915613769896</y>
        <heading>0.0</heading>
        <isVertex>false</isVertex>
    </Pose>
    <Pose>
        <x>10.928077571488458</x>
        <y>69.82414720122871</y>
        <heading>0.0</heading>
        <isVertex>false</isVertex>
    </Pose>
    <Pose>
        <x>11.286351074465758</x>
        <y>70.0020088435301</y>
        <heading>0.0</heading>
        <isVertex>false</isVertex>
    </Pose>
    <Pose>
        <x>11.648109920832841</x>
        <y>70.17266992231767</y>
        <heading>0.0</heading>
        <isVertex>false</isVertex>
    </Pose>
    <Pose>
        <x>12.01320941187454</x>
        <y>70.33606217543533</y>
        <heading>0.0</heading>
        <isVertex>false</isVertex>
    </Pose>
    <Pose>
        <x>12.381503512662366</x>
        <y>70.4921202481604</y>
        <heading>0.0</heading>
        <isVertex>false</isVertex>
    </Pose>
    <Pose>
        <x>12.752844910466532</x>
        <y>70.64078171934453</y>
        <heading>0.0</heading>
        <isVertex>false</isVertex>
    </Pose>
    <Pose>
        <x>13.127085073679064</x>
        <y>70.78198712638135</y>
        <heading>0.0</heading>
        <isVertex>false</isVertex>
    </Pose>
    <Pose>
        <x>13.504074311224478</x>
        <y>70.91567998899077</y>
        <heading>0.0</heading>
        <isVertex>false</isVertex>
    </Pose>
    <Pose>
        <x>13.883661832434218</x>
        <y>71.04180683181032</y>
        <heading>0.0</heading>
        <isVertex>false</isVertex>
    </Pose>
    <Pose>
        <x>14.265695807360894</x>
        <y>71.16031720578451</y>
        <heading>0.0</heading>
        <isVertex>false</isVertex>
    </Pose>
    <Pose>
        <x>14.650023427508257</x>
        <y>71.27116370834386</y>
        <heading>0.0</heading>
        <isVertex>false</isVertex>
    </Pose>
    <Pose>
        <x>15.036490966952545</x>
        <y>71.37430200236531</y>
        <heading>0.0</heading>
        <isVertex>false</isVertex>
    </Pose>
    <Pose>
        <x>15.424943843830818</x>
        <y>71.46969083390638</y>
        <heading>0.0</heading>
        <isVertex>false</isVertex>
    </Pose>
    <Pose>
        <x>15.81522668217162</x>
        <y>71.55729204870633</y>
        <heading>0.0</heading>
        <isVertex>false</isVertex>
    </Pose>
    <Pose>
        <x>16.207183374043318</x>
        <y>71.6370706074472</y>
        <heading>0.0</heading>
        <isVertex>false</isVertex>
    </Pose>
    <Pose>
        <x>16.60065714199519</x>
        <y>71.7089945997692</y>
        <heading>0.0</heading>
        <isVertex>false</isVertex>
    </Pose>
    <Pose>
        <x>16.995490601766292</x>
        <y>71.7730352570344</y>
        <heading>0.0</heading>
        <isVertex>false</isVertex>
    </Pose>
    <Pose>
        <x>17.391525825237096</x>
        <y>71.82916696383373</y>
        <heading>0.0</heading>
        <isVertex>false</isVertex>
    </Pose>
    <Pose>
        <x>17.78860440359861</x>
        <y>71.8773672682329</y>
        <heading>0.0</heading>
        <isVertex>false</isVertex>
    </Pose>
    <Pose>
        <x>18.18656751071381</x>
        <y>71.9176168907528</y>
        <heading>0.0</heading>
        <isVertex>false</isVertex>
    </Pose>
    <Pose>
        <x>18.585255966645946</x>
        <y>71.9498997320811</y>
        <heading>0.0</heading>
        <isVertex>false</isVertex>
    </Pose>
    <Pose>
        <x>18.98451030132842</x>
        <y>71.97420287951167</y>
        <heading>0.0</heading>
        <isVertex>false</isVertex>
    </Pose>
    <Pose>
        <x>19.384170818350682</x>
        <y>71.99051661210959</y>
        <heading>0.0</heading>
        <isVertex>false</isVertex>
    </Pose>
    <Pose>
        <x>19.784077658834658</x>
        <y>71.99883440459932</y>
        <heading>0.0</heading>
        <isVertex>false</isVertex>
    </Pose>
    <Pose>
        <x>20.18407086537617</x>
        <y>71.9991529299748</y>
        <heading>0.0</heading>
        <isVertex>false</isVertex>
    </Pose>
    <Pose>
        <x>20.0</x>
        <y>72.0</y>
        <heading>50.0</heading>
        <isVertex>false</isVertex>
    </Pose>
    <Pose>
        <x>20.4</x>
        <y>72.0</y>
        <heading>51.0</heading>
        <isVertex>false</isVertex>
    </Pose>
    <Pose>
        <x>20.8</x>
        <y>72.0</y>
        <heading>52.0</heading>
        <isVertex>false</isVertex>
    </Pose>
    <Pose>
        <x>21.2</x>
        <y>72.0</y>
        <heading>53.0</heading>
        <isVertex>false</isVertex>
    </Pose>
    <Pose>
        <x>21.6</x>
        <y>72.0</y>
        <heading>54.0</heading>
        <isVertex>false</isVertex>
    </Pose>
    <Pose>
        <x>22.0</x>
        <y>72.0</y>
        <heading>55.0</heading>
        <isVertex>false</isVertex>
    </Pose>
    <Pose>
        <x>22.4</x>
        <y>72.0</y>
        <heading>56.0</heading>
        <isVertex>false</isVertex>
    </Pose>
    <Pose>
        <x>22.8</x>
        <y>72.0</y>
        <heading>57.0</heading>
        <isVertex>false</isVertex>
    </Pose>
    <Pose>
        <x>23.2</x>
        <y>72.0</y>
        <heading>58.0</heading>
        <isVertex>false</isVertex>
    </Pose>
    <Pose>
        <x>23.6</x>
        <y>72.0</y>
        <heading>59.0</heading>
        <isVertex>false</isVertex>
    </Pose>
    <Pose>
        <x>24.0</x>
        <y>72.0</y>
        <heading>60.0</heading>
        <isVertex>false</isVertex>
    </Pose>
    <Pose>
        <x>24.4</x>
        <y>72.0</y>
        <heading>61.0</heading>
        <isVertex>false</isVertex>
    </Pose>
    <Pose>
        <x>24.8</x>
        <y>72.0</y>
        <heading>62.0</heading>
        <isVertex>false</isVertex>
    </Pose>
    <Pose>
        <x>25.2</x>
        <y>72.0</y>
        <heading>63.0</heading>
        <isVertex>false</isVertex>
    </Pose>
    <Pose>
        <x>25.6</x>
        <y>72.0</y>
        <heading>64.0</heading>
        <isVertex>false</isVertex>
    </Pose>
    <Pose>
        <x>26.0</x>
        <y>72.0</y>
        <heading>65.0</heading>
        <isVertex>false</isVertex>
    </Pose>
    <Pose>
        <x>26.4</x>
        <y>72.0</y>
        <heading>66.0</heading>
        <isVertex>false</isVertex>
    </Pose>
    <Pose>
        <x>26.8</x>
        <y>72.0</y>
        <heading>67.0</heading>
        <isVertex>false</isVertex>
    </Pose>
    <Pose>
        <x>27.2</x>
        <y>72.0</y>
        <heading>68.0</heading>
        <isVertex>false</isVertex>
    </Pose>
    <Pose>
        <x>27.6</x>
        <y>72.0</y>
        <heading>69.0</heading>
        <isVertex>false</isVertex>
    </Pose>
    <Pose>
        <x>28.0</x>
        <y>72.0</y>
        <heading>70.0</heading>
        <isVertex>false</isVertex>
    </Pose>
    <Pose>
        <x>28.4</x>
        <y>72.0</y>
        <heading>71.0</heading>
        <isVertex>false</isVertex>
    </Pose>
    <Pose>
        <x>28.8</x>
        <y>72.0</y>
        <heading>72.0</heading>
        <isVertex>false</isVertex>
    </Pose>
    <Pose>
        <x>29.2</x>
        <y>72.0</y>
        <heading>73.0</heading>
        <isVertex>false</isVertex>
    </Pose>
    <Pose>
        <x>29.6</x>
        <y>72.0</y>
        <heading>74.0</heading>
        <isVertex>false</isVertex>
    </Pose>
    <Pose>
        <x>30.0</x>
        <y>72.0</y>
        <heading>75.0</heading>
        <isVertex>false</isVertex>
    </Pose>
    <Pose>
        <x>30.4</x>
        <y>72.0</y>
        <heading>76.0</heading>
        <isVertex>false</isVertex>
    </Pose>
    <Pose>
        <x>30.8</x>
        <y>72.0</y>
        <heading>77.0</heading>
        <isVertex>false</isVertex>
    </Pose>
    <Pose>
        <x>31.2</x>
        <y>72.0</y>
        <heading>78.0</heading>
        <isVertex>false</isVertex>
    </Pose>
    <Pose>
        <x>31.6</x>
        <y>72.0</y>
        <heading>79.0</heading>
        <isVertex>false</isVertex>
    </Pose>
    <Pose>
        <x>32.0</x>
        <y>72.0</y>
        <heading>80.0</heading>
        <isVertex>false</isVertex>
    </Pose>
    <Pose>
        <x>32.4</x>
        <y>72.0</y>
        <heading>81.0</heading>
        <isVertex>false</isVertex>
    </Pose>
    <Pose>
        <x>32.8</x>
        <y>72.0</y>
        <heading>82.0</heading>
        <isVertex>false</isVertex>
    </Pose>
    <Pose>
        <x>33.2</x>
        <y>72.0</y>
        <heading>83.0</heading>
        <isVertex>false</isVertex>
    </Pose>
    <Pose>
        <x>33.6</x>
        <y>72.0</y>
        <heading>84.0</heading>
        <isVertex>false</isVertex>
    </Pose>
    <Pose>
        <x>34.0</x>
        <y>72.0</y>
        <heading>85.0</heading>
        <isVertex>false</isVertex>
    </Pose>
    <Pose>
        <x>34.4</x>
        <y>72.0</y>
        <heading>86.0</heading>
        <isVertex>false</isVertex>
    </Pose>
    <Pose>
        <x>34.8</x>
        <y>72.0</y>
        <heading>87.0</heading>
        <isVertex>false</isVertex>
    </Pose>
    <Pose>
        <x>35.2</x>
        <y>72.0</y>
        <heading>88.0</heading>
        <isVertex>false</isVertex>
    </Pose>
    <Pose>
        <x>35.6</x>
        <y>72.0</y>
        <heading>89.0</heading>
        <isVertex>false</isVertex>
    </Pose>
    <Pose>
        <x>36.0</x>
        <y>72.0</y>
        <heading>90.0</heading>
        <isVertex>false</isVertex>
    </Pose>
    <Pose>
        <x>36.0</x>
        <y>72.0</y>
        <heading>90.0</heading>
        <isVertex>true</isVertex>
    </Pose>
    <age>0</age>
</Path>
